LICENSE
MANIFEST.in
README.rst
setup.py
osxnotify_cffi/__init__.py
osxnotify_cffi/meta.py
osxnotify_cffi/osxnotify_cffi.py
osxnotify_cffi.egg-info/PKG-INFO
osxnotify_cffi.egg-info/SOURCES.txt
osxnotify_cffi.egg-info/dependency_links.txt
osxnotify_cffi.egg-info/requires.txt
osxnotify_cffi.egg-info/top_level.txt