Metadata-Version: 1.1
Name: osxnotify-cffi
Version: 1.0
Summary: No nonsense OS X notifications for Python scripts (CFFI wrapper)
Home-page: https://github.com/tomekwojcik/osxnotify-python-cffi
Author: Tomek Wójcik
Author-email: tomek@bthlabs.pl
License: MIT
Download-URL: http://github.com/tomekwojcik/osxnotify-python-cffi/tarball/v1.0
Platform: UNKNOWN
Classifier: Development Status :: 4 - Beta
Classifier: Environment :: MacOS X :: Cocoa
Classifier: Intended Audience :: Developers
Classifier: License :: OSI Approved :: MIT License
Classifier: Operating System :: MacOS :: MacOS X
Classifier: Programming Language :: Python :: 2.7
Classifier: Programming Language :: Python :: 3.4
Classifier: Topic :: Software Development :: Libraries :: Python Modules
